avroknife-1.0.5.data/scripts/avroknife
avroknife/file_system.pyc
avroknife/utils.pyc
avroknife/operations.pyc
avroknife/error.py
avroknife/operations.py
avroknife/error.pyc
avroknife/printer.py
avroknife/utils.py
avroknife/__init__.pyc
avroknife/record_selector.py
avroknife/file_system.py
avroknife/__init__.py
avroknife/data_store.pyc
avroknife/RELEASE-VERSION~
avroknife/data_store.py
avroknife/printer.pyc
avroknife/record_selector.pyc
avroknife/RELEASE-VERSION
avroknife/test/command_line_runner.py
avroknife/test/file_system.pyc
avroknife/test/tools.pyc
avroknife/test/tools_test.py
avroknife/test/tests.pyc
avroknife/test/tools.py
avroknife/test/tools_test.pyc
avroknife/test/__init__.pyc
avroknife/test/tests.py
avroknife/test/file_system.py
avroknife/test/example_data_stores.py
avroknife/test/command_line_runner.pyc
avroknife/test/__init__.py
avroknife/test/example_data_stores.pyc
avroknife/test/data/nested.avsc
avroknife/test/data/binary.avsc
avroknife/test/data/user.avsc
avroknife/test/data/binary_stuff/various_stuff.tar.gz
avroknife/test/data/binary_stuff/greetings.tar.gz
avroknife/test/data/local_input_dir/user_projection.avsc
avroknife-1.0.5.dist-info/DESCRIPTION.rst
avroknife-1.0.5.dist-info/WHEEL
avroknife-1.0.5.dist-info/RECORD
avroknife-1.0.5.dist-info/metadata.json
avroknife-1.0.5.dist-info/top_level.txt
avroknife-1.0.5.dist-info/METADATA
