Metadata-Version: 2.0
Name: avroknife
Version: 1.0.5
Summary: Utility for browsing and simple manipulation of Avro-based files
Home-page: https://github.com/CeON/avroknife
Author: Mateusz Kobos, Pawel Szostek
Author-email: mkobos@icm.edu.pl
License: Apache License, Version 2.0
Keywords: Avro,browsing,manipulation
Platform: UNKNOWN
Classifier: Development Status :: 5 - Production/Stable    
Classifier: Environment :: Console
Classifier: Intended Audience :: Developers
Classifier: Programming Language :: Python
Classifier: Programming Language :: Python :: 2.7
Classifier: License :: OSI Approved :: Apache Software License
Classifier: Topic :: Scientific/Engineering :: Information Analysis
Classifier: Operating System :: POSIX :: Linux
Requires-Dist: avro (>=1.7.5)
Requires-Dist: nose
